{
  "timestamp": "2025-11-01T14:20:19.932272",
  "assessment_type": "FINAL_SIMPLE_HONEST_ASSESSMENT",
  "what_we_accomplished": {
    "oauth_infrastructure": "100% complete",
    "credential_management": "100% complete",
    "authentication_foundation": "100% complete",
    "real_credentials": "9/9 services configured"
  },
  "whats_missing": {
    "user_interface": "0% complete",
    "application_backend": "50% complete",
    "service_integration": "0% complete",
    "user_experience": "0% available"
  },
  "marketing_claims_reality": [
    {
      "claim": "Production Ready",
      "reality": "OAuth infrastructure ready, application missing",
      "honest": "PARTIALLY TRUE"
    },
    {
      "claim": "33+ Integrated Platforms",
      "reality": "9 OAuth services configured, 0 integrated",
      "honest": "FALSE"
    },
    {
      "claim": "95% UI Coverage",
      "reality": "0% UI components implemented",
      "honest": "FALSE"
    },
    {
      "claim": "Workflow Automation UI",
      "reality": "No automation UI exists",
      "honest": "FALSE"
    },
    {
      "claim": "Real Service Integrations",
      "reality": "OAuth credentials only, no integration",
      "honest": "FALSE"
    }
  ],
  "recommendations": [
    "build_user_interface",
    "implement_application_backend",
    "create_service_integrations",
    "test_complete_user_journeys"
  ],
  "final_assessment": {
    "oauth_success": "100%",
    "app_success": "0%",
    "overall_status": "oauth_infrastructure_ready",
    "production_ready": false,
    "developer_ready": true
  }
}